slack_bot/__init__.py
slack_bot/bot.py
slack_bot/models.py
slack_bot/routes.py
slack_bot-0.0.2.dist-info/LICENSE
slack_bot-0.0.2.dist-info/METADATA
slack_bot-0.0.2.dist-info/WHEEL
slack_bot-0.0.2.dist-info/top_level.txt
slack_bot-0.0.2.dist-info/RECORD
