Metadata-Version: 2.1
Name: slack-bot
Version: 0.0.2
Summary: Simple application for make slack bot
Home-page: https://github.com/DKorytkin/slack-bot
Author: Denis Korytkin
Author-email: dkorytkin@gmail.com
License: MIT license
Keywords: bot,slack,app,slack_bot,app,application
Platform: linux
Classifier: Development Status :: 2 - Pre-Alpha
Classifier: Programming Language :: Python :: 3.6
Classifier: Programming Language :: Python :: 3.7
Classifier: Topic :: Software Development :: Libraries
Classifier: Topic :: Software Development :: Libraries :: Application Frameworks
Classifier: Topic :: Software Development :: Libraries :: Python Modules
Classifier: License :: OSI Approved :: MIT License
Requires-Python: >=3.6
Requires-Dist: pip (==19.0.3)
Requires-Dist: setuptools (==41.0.0)
Requires-Dist: certifi (==2019.3.9)
Requires-Dist: chardet (==3.0.4)
Requires-Dist: idna (==2.8)
Requires-Dist: requests (==2.21.0)
Requires-Dist: six (==1.12.0)
Requires-Dist: urllib3 (==1.24.2)
Requires-Dist: websocket-client (==0.47.0)
Requires-Dist: slackclient (==1.3.1)
Requires-Dist: parse (==1.12.0)
Provides-Extra: tests
Requires-Dist: atomicwrites (==1.3.0) ; extra == 'tests'
Requires-Dist: attrs (==19.1.0) ; extra == 'tests'
Requires-Dist: more-itertools (==7.0.0) ; extra == 'tests'
Requires-Dist: pluggy (==0.9.0) ; extra == 'tests'
Requires-Dist: py (==1.8.0) ; extra == 'tests'
Requires-Dist: Pygments (==2.3.1) ; extra == 'tests'
Requires-Dist: bleach (==3.1.0) ; extra == 'tests'
Requires-Dist: docutils (==0.14) ; extra == 'tests'
Requires-Dist: pkginfo (==1.5.0.1) ; extra == 'tests'
Requires-Dist: readme-renderer (==24.0) ; extra == 'tests'
Requires-Dist: requests-toolbelt (==0.9.1) ; extra == 'tests'
Requires-Dist: tqdm (==4.31.1) ; extra == 'tests'
Requires-Dist: webencodings (==0.5.1) ; extra == 'tests'
Requires-Dist: pytest (==4.4.1) ; extra == 'tests'
Requires-Dist: wheel (==0.33.1) ; extra == 'tests'
Requires-Dist: twine (==1.13.0) ; extra == 'tests'
